{"id":30008,"avatar":"//lain.bgm.tv/pic/user/m/000/07/93/79332.jpg","floor":"#1","group":"靠谱人生茶话会","groupHref":"/group/boring","groupThumb":"//lain.bgm.tv/pic/icon/m/000/00/03/364.jpg","message":"我妹妹跟我说最近和她男友吵架了。她们谈了有3年多，每年有半年在异国恋。<br>       原因是我妹妹说她男友和某女生网上聊得有点多，就半开玩笑的说，能不能不聊这么多，有她没有我的咧。结果他男友就发脾气了，说她总是无理取闹，不理我妹妹了。       <br><br>        我妹妹最近去找他道歉了几次，他每次都说自己想一个人静一静，两个人暂时分开一个月，看她表现。最后电话都设成拒接了，微信QQ都不回。  我妹妹都后来都去求他了，还问他是不是分手的意思，他有不说，就说要自己待一会儿，话说我妹妹越找他越烦。<br>        目前他是假期这一个月一过就又不在国内了.....我妹妹现在很难过，不知道怎么办。   她说等一个月他不在了就真的说不定没希望了。 <br><br>希望BGM的大家帮忙看看，告诉一下怎么挽救。<br><br>我心里的推断很清楚结局是什么，可是我真的很心疼我妹妹，她难过我整个人都不好了，拜托大家帮帮忙！万分感谢 ","time":"2013-12-11 18:35","title":"【婚恋问题】求BGM感情大神帮帮忙分析给建议","userId":"dido","userName":"Shionji有子","userSign":"(教练，我想打篮球！)"}