{"id":375642,"avatar":"//lain.bgm.tv/pic/user/m/000/67/48/674893.jpg","floor":"#1","group":"靠谱人生茶话会","groupHref":"/group/boring","groupThumb":"//lain.bgm.tv/pic/icon/m/000/00/03/364.jpg","message":"<a href=\"https://imgse.com/i/z4y4mt\" target=\"_blank\" rel=\"nofollow external noopener noreferrer\" class=\"l\"><img src=\"https://s1.ax1x.com/2022/12/12/z4y4mt.jpg\" class=\"code\" rel=\"noreferrer\" referrerpolicy=\"no-referrer\" alt></a> ","time":"2022-12-12 22:34","title":"肥王复活赛打赢了","userId":"kanya","userName":"762","userSign":"(你知道阿基米德原理吗)"}