{"id":5130,"avatar":"//lain.bgm.tv/pic/user/m/000/00/06/610.jpg","floor":"#1","group":"上厕所不洗手小组","groupHref":"/group/fighters","groupThumb":"//lain.bgm.tv/pic/icon/m/000/00/06/671.jpg","message":"3D格斗游戏大家都使用什么角色呢？<br>图列：（可自添<br><img src=\"http://bgm.tv/pic/photo/l/00/ac/610_Ps7WP.jpg\" class=\"code\" alt><br><br>我的<br><img src=\"http://bgm.tv/pic/photo/l/00/ac/610_784u8.jpg\" class=\"code\" alt><br><br><br>PS: Street fighter IV, Mortal Kombat 这类2d转3d的就不调查了<br>PS2:拳击类的...也不调查了... ","time":"2011-4-6 16:43","title":"3D格斗游戏主要使用角色","userId":"speetania","userName":"EISSAC","userSign":"(, the Bar-player)"}