{"id":6424,"avatar":"//lain.bgm.tv/pic/user/m/000/00/70/7088.jpg","floor":"#1","group":"靠谱人生茶话会","groupHref":"/group/boring","groupThumb":"//lain.bgm.tv/pic/icon/m/000/00/03/364.jpg","message":"<a href=\"http://www.songtaste.com/song/8867/\" target=\"_blank\" rel=\"nofollow external noopener\" class=\"l\">http://www.songtaste.com/song/8867/</a><br><a href=\"http://v.youku.com/v_show/id_XMTk0OTY1NzI4.html\" target=\"_blank\" rel=\"nofollow external noopener\" class=\"l\">http://v.youku.com/v_show/id_XMTk0OTY1NzI4.html</a><br>心情不好习惯听歌 ","time":"2011-6-22 00:39","title":"为什么觉得BGM的人最近心情都不好","userId":"s23sui","userName":"ドール","userSign":""}