{"id":311323,"avatar":"//lain.bgm.tv/pic/user/m/000/06/50/65077.jpg","floor":"#1","group":"番組WIKI計画","groupHref":"/group/wiki","groupThumb":"//lain.bgm.tv/pic/icon/m/000/00/01/128.jpg","message":"如题，不知道bangumi这有没有喜欢体育混虎扑论坛的同道中人<br><br>虎扑看帖子一直有一个点亮机制，大家可以把自己觉得有优点亮点槽点黑点的回复，通过点亮或者你可以理解为点赞的次数把这条回复顶到显眼的位置<br><br>我觉得能应用到作品页面上吐槽箱<br><br>我觉得吐槽箱是一个很好的作品口碑具象化的平台，当然也充斥着各种良莠不齐的吐槽<br><br>很多优秀的点评又容易埋没在浩瀚的文字潮流里<br><br>如果能把吐槽箱里优秀的吐槽点评能以这种方式来置顶，也算是给没接触这部作品的新人一个更有挑逗性的介绍<br><br>嘛，映像里我很多片子补番都是翻吐槽箱查阅大家吐槽时候被一些神回复激起深深的兴趣——我有特殊的安利方式 唉嘿 ","time":"2015-7-22 19:51","title":"关于吐槽箱改进的一点想法","userId":"theduke","userName":"愛の騎士duke","userSign":"(无法触及因而耀眼，贪得无厌而又毫不眷恋 ... ... ... ...)"}