{"id":35318,"avatar":"//lain.bgm.tv/pic/user/m/000/15/77/157769.jpg","floor":"#1","group":"读书会","groupHref":"/group/read","groupThumb":"//lain.bgm.tv/pic/icon/m/000/00/12/1292.jpg?r=1350106915","message":"相信人可以穿越时空吗？<br>你对主席有怎样的认识和了解？<br>你是否了解1959年召开的第一次庐山会议？<br>如果你穿越了时空，你会如何在另一个时空生存下去？<br>如果你有机会成为主席身边的一名被他信任的人，你会做些什么？<br>如果你有机会将你在未来的知道的一切告诉主席，你会告诉他吗？<br>如果你对主席有了近距离的接触和更深的了解，你会爱上他吗？<br>如果你对主席产生了让你害怕的异样感情，你会如何对待？<br>如果你有机会留在过去，留在主席身边，你会舍弃你的时代为他留下吗？<br>这些“如果”你可能一生都遇不到一个，但是陈渺却意外地都遇到了，那么她这个未来人会怎样抉择呢？就是下面这个故事将要讲述的……<br><img src=\"http://ww3.sinaimg.cn/mw600/695e3821gw1ei0irhh10ij20fi07st92.jpg\" class=\"code\" alt> ","time":"2014-9-3 12:52","title":"你们有谁看过这本书？","userId":"x0","userName":"‬","userSign":""}