{"id":372826,"avatar":"//lain.bgm.tv/pic/user/m/000/54/64/546484.jpg","floor":"#1","group":"靠谱人生茶话会","groupHref":"/group/boring","groupThumb":"//lain.bgm.tv/pic/icon/m/000/00/03/364.jpg","message":"<a href=\"https://gogoanime.ee/toradora-episode-1\" target=\"_blank\" rel=\"nofollow external noopener noreferrer\" class=\"l\">https://gogoanime.ee/toradora-episode-1</a><br>idm可以一集一集的手动下，有点麻烦..... ","time":"2022-9-6 12:06","title":"什么插件可以批量抓取视频吗","userId":"546484","userName":"Nevermore","userSign":"(Make that money；Watch it burn)"}