{"id":32635,"avatar":"//lain.bgm.tv/pic/user/m/000/20/20/202030.jpg","floor":"#1","group":"番組WIKI計画","groupHref":"/group/wiki","groupThumb":"//lain.bgm.tv/pic/icon/m/000/00/01/128.jpg","message":"嗯，問題同上<br>在下是電子遊戲的狂熱愛好者啦<br>見到Bangumi的遊戲分類中，許多無論是上世代的經典亦或是本世代的流行都缺乏相應詞條或者相應詞條信息<br>例如極度恐慌【F·E·A·R First Encounter Assault Recon】的詞條完全是空的說、輻射系列的相關條目竟然把鋼鐵兄弟會和廢土給漏了（當然，同樣是沒有詞條）……還有好幾個戰錘遊戲的信息也是有待改善的，黑魂的也是……<br>本著對遊戲的愛開始收集素材，發現自己並沒有權力編輯詞條誒 ","time":"2014-5-24 21:08","title":"啊拉，普通會員沒辦法修改詞條么？","userId":"veritas","userName":"Veritas","userSign":"(設計學攻略中)"}