{"id":370927,"avatar":"//lain.bgm.tv/pic/user/m/000/70/19/701997.jpg","floor":"#1","group":"靠谱人生茶话会","groupHref":"/group/boring","groupThumb":"//lain.bgm.tv/pic/icon/m/000/00/03/364.jpg","message":"看了几个小排球的片段觉得挺不错，就试着补来着，然而看着看着总觉得哪里不对，仔细想想从之前网王开始就察觉出这种微妙的违和感，到后来黑蓝啊，free啊，尤里啊这些更是。但有些体育番就能看下去，SD，megalobox，强风吹拂。我就琢磨了一下能看进去和不能看进去的这两种体育番，发现我看不下去的那些有个特征——太清爽了。哪怕是运动到虚脱暴汗也能保持清爽的发型，出个汗跟美人出浴一样！所以这个违和感应该是察觉出和现实体验的割裂，毕竟高强度运动后任谁都是一身臭汗脏兮兮的，发型早就乱七八糟了，汗液是有些浑浊的，不是那种晶莹剔透的感觉，表情也会因面部代偿而扭曲。 ","time":"2022-6-23 04:59","title":"尝试补运动番失败，试着找了找原因","userId":"701997","userName":"lewdoyster","userSign":"(you are all I long for all I worship and adore)"}