{"id":381684,"avatar":"//lain.bgm.tv/pic/user/m/000/26/58/265851.jpg","floor":"#1","group":"靠谱人生茶话会","groupHref":"/group/boring","groupThumb":"//lain.bgm.tv/pic/icon/m/000/00/03/364.jpg","message":"<a href=\"https://www.animesenpai.net/the-largest-anime-database-myanimelast-reportedly-hacked/\" target=\"_blank\" rel=\"nofollow external noopener noreferrer\" class=\"l\">https://www.animesenpai.net/the- ... -reportedly-hacked/</a><br><br><a href=\"https://imgse.com/i/p969c8I\" target=\"_blank\" rel=\"nofollow external noopener noreferrer\" class=\"l\"><img src=\"https://s1.ax1x.com/2023/05/13/p969c8I.jpg\" class=\"code\" rel=\"noreferrer\" referrerpolicy=\"no-referrer\" alt></a><br><br>图中我们可以看到大量动画名称改为“Lets All Love Lain”<br><br>Present day, present time，hahahahahaha！ ","time":"2023-5-13 00:40","title":"myanimelist被黑客攻击，所有动画标题都被篡改为“Lets All Love Lain”","userId":"265851","userName":"灼霞","userSign":"(拥抱中毒者)"}