{"id":33104,"avatar":"//lain.bgm.tv/pic/user/m/000/04/63/46380.jpg","floor":"#1","group":"neta","groupHref":"/group/neta","groupThumb":"//lain.bgm.tv/pic/icon/m/000/00/11/1151.jpg?r=1334345049","message":"更新于 2014-08-26<br>以后将于 <a href=\"http://bgm.tv/group/topic/33997\" target=\"_blank\" rel=\"nofollow external noopener\" class=\"l\">EP2</a> 更新。<br><p align=\"center\">================================<br><img src=\"http://1.loli.io/F7fqIr.jpg\" class=\"code\" alt><br>↑<a href=\"http://bgm.tv/subject/5655\" target=\"_blank\" rel=\"nofollow external noopener\" class=\"l\">世紀末オカルト学院</a> ep.7↑<br><img src=\"http://r.loli.io/bQJn2u.jpg\" class=\"code\" alt><br><img src=\"http://r.loli.io/juQRBb.jpg\" class=\"code\" alt><br><img src=\"http://r.loli.io/nyMra2.jpg\" class=\"code\" alt><br><img src=\"http://r.loli.io/fQr2Uv.jpg\" class=\"code\" alt><br><img src=\"http://r.loli.io/u6ZBvm.jpg\" class=\"code\" alt><br><img src=\"http://r.loli.io/2QnmYb.jpg\" class=\"code\" alt><br><img src=\"http://r.loli.io/77fI3e.jpg\" class=\"code\" alt><br><img src=\"http://r.loli.io/mU3YVr.jpg\" class=\"code\" alt><br><img src=\"http://r.loli.io/NZ77j2.jpg\" class=\"code\" alt><br><img src=\"http://r.loli.io/mMraMb.jpg\" class=\"code\" alt><br>↑<a href=\"http://bgm.tv/subject/10440\" target=\"_blank\" rel=\"nofollow external noopener\" class=\"l\">あの日見た花の名前を僕達はまだ知らない。</a> ep.10↑<br><img src=\"http://r.loli.io/7JbU3m.jpg\" class=\"code\" alt><br><img src=\"http://r.loli.io/YnAbM3.jpg\" class=\"code\" alt><br><img src=\"http://r.loli.io/bUFnM3.jpg\" class=\"code\" alt><br><img src=\"http://r.loli.io/A7fQni.jpg\" class=\"code\" alt><br>↑涼宮ハルヒの憂鬱 ep.6(<a href=\"http://bgm.tv/subject/485\" target=\"_blank\" rel=\"nofollow external noopener\" class=\"l\">2006</a>)/ep.10(<a href=\"http://bgm.tv/subject/1606\" target=\"_blank\" rel=\"nofollow external noopener\" class=\"l\">2009</a>)↑<br><img src=\"http://r.loli.io/7rUFza.jpg\" class=\"code\" alt><br><img src=\"http://r.loli.io/vAni6f.jpg\" class=\"code\" alt><br><img src=\"http://r.loli.io/6322Ur.jpg\" class=\"code\" alt><br><img src=\"http://r.loli.io/BNVjUb.jpg\" class=\"code\" alt><br><img src=\"http://r.loli.io/nIf6fu.jpg\" class=\"code\" alt><br><img src=\"http://r.loli.io/I3u22e.jpg\" class=\"code\" alt><br><img src=\"http://r.loli.io/QJZFbi.jpg\" class=\"code\" alt><br><img src=\"http://r.loli.io/RjIry2.jpg\" class=\"code\" alt><br><img src=\"http://r.loli.io/iAjAZf.jpg\" class=\"code\" alt><br><img src=\"http://r.loli.io/Nr6Rn2.jpg\" class=\"code\" alt><br><img src=\"http://r.loli.io/qINnau.jpg\" class=\"code\" alt><br><img src=\"http://r.loli.io/JRJ7fq.jpg\" class=\"code\" alt><br><img src=\"http://r.loli.io/Afmym2.jpg\" class=\"code\" alt><br><img src=\"http://r.loli.io/mEfiay.jpg\" class=\"code\" alt><br><img src=\"http://r.loli.io/jmqMb2.jpg\" class=\"code\" alt><br><img src=\"http://r.loli.io/zArEbq.jpg\" class=\"code\" alt><br>↑<a href=\"http://bgm.tv/subject/1606\" target=\"_blank\" rel=\"nofollow external noopener\" class=\"l\">涼宮ハルヒの憂鬱</a> ep.12-19(2009)↑<br><img src=\"http://r.loli.io/NJVNja.jpg\" class=\"code\" alt><br>↑<a href=\"http://bgm.tv/subject/12544\" target=\"_blank\" rel=\"nofollow external noopener\" class=\"l\">蛍火の杜へ</a>↑<br><img src=\"http://r.loli.io/qMNvMb.jpg\" class=\"code\" alt><br><img src=\"http://r.loli.io/b67Fzu.jpg\" class=\"code\" alt><br><img src=\"http://r.loli.io/2yUnQb.jpg\" class=\"code\" alt><br>↑<a href=\"http://bgm.tv/subject/259\" target=\"_blank\" rel=\"nofollow external noopener\" class=\"l\">夏目友人帳</a> ep.13↑<br><img src=\"http://r.loli.io/EbMry2.jpg\" class=\"code\" alt><br><img src=\"http://r.loli.io/n6n2ei.jpg\" class=\"code\" alt><br><img src=\"http://r.loli.io/RBbMza.jpg\" class=\"code\" alt><br><img src=\"http://r.loli.io/63yqUn.jpg\" class=\"code\" alt><br>↑<a href=\"http://bgm.tv/subject/12536\" target=\"_blank\" rel=\"nofollow external noopener\" class=\"l\">夏目友人帳 参</a> ED↑<br><img src=\"http://r.loli.io/eIBb22.jpg\" class=\"code\" alt><br>↑<a href=\"http://bgm.tv/subject/2611\" target=\"_blank\" rel=\"nofollow external noopener\" class=\"l\">天体戦士サンレッド 第2期</a> ED↑<br><img src=\"http://r.loli.io/bmiMba.jpg\" class=\"code\" alt><br>↑<a href=\"http://bgm.tv/subject/2710\" target=\"_blank\" rel=\"nofollow external noopener\" class=\"l\">風人物語</a> ep.2↑<br><img src=\"http://r.loli.io/auI3Ur.jpg\" class=\"code\" alt><br><img src=\"http://r.loli.io/aq2Anu.jpg\" class=\"code\" alt><br><img src=\"http://r.loli.io/7VvUZ3.jpg\" class=\"code\" alt><br><img src=\"http://r.loli.io/NFbyQj.jpg\" class=\"code\" alt><br><img src=\"http://r.loli.io/JrIvQv.jpg\" class=\"code\" alt><br><img src=\"http://r.loli.io/MNRBbe.jpg\" class=\"code\" alt><br><img src=\"http://r.loli.io/Yryyii.jpg\" class=\"code\" alt><br>↑<a href=\"http://bgm.tv/subject/18605\" target=\"_blank\" rel=\"nofollow external noopener\" class=\"l\">たまゆら〜hitotose〜</a> ep.5.5↑<br><img src=\"http://r.loli.io/zyAV3m.jpg\" class=\"code\" alt><br><img src=\"http://r.loli.io/uYrIVz.jpg\" class=\"code\" alt><br><img src=\"http://r.loli.io/B3MBnu.jpg\" class=\"code\" alt><br><img src=\"http://r.loli.io/fA3Yjm.jpg\" class=\"code\" alt><br>↑<a href=\"http://bgm.tv/subject/45213\" target=\"_blank\" rel=\"nofollow external noopener\" class=\"l\">たまゆら〜もあぐれっしぶ〜</a> ep.7↑<br><img src=\"http://r.loli.io/yMn2ya.jpg\" class=\"code\" alt><br><img src=\"http://r.loli.io/mUnEVj.jpg\" class=\"code\" alt><br><img src=\"http://r.loli.io/qiAFJn.jpg\" class=\"code\" alt><br><img src=\"http://r.loli.io/FzAJfe.jpg\" class=\"code\" alt><br>↑<a href=\"http://bgm.tv/subject/3994\" target=\"_blank\" rel=\"nofollow external noopener\" class=\"l\">スケッチブック ～full color's～</a> ep.3↑<br><img src=\"http://r.loli.io/E7vu6z.jpg\" class=\"code\" alt><br><img src=\"http://r.loli.io/UFjmAr.jpg\" class=\"code\" alt><br><img src=\"http://r.loli.io/nmEJvu.jpg\" class=\"code\" alt><br><img src=\"http://r.loli.io/YrQjEj.jpg\" class=\"code\" alt><br>↑<a href=\"http://bgm.tv/subject/909\" target=\"_blank\" rel=\"nofollow external noopener\" class=\"l\">とらドラ！</a> ep.10↑<br><img src=\"http://r.loli.io/QNvMfq.jpg\" class=\"code\" alt><br><img src=\"http://r.loli.io/2A7v6b.jpg\" class=\"code\" alt><br>↑<a href=\"http://bgm.tv/subject/47533\" target=\"_blank\" rel=\"nofollow external noopener\" class=\"l\">謎の彼女X OAD 謎の夏祭り</a>↑<br><img src=\"http://r.loli.io/B77nq2.jpg\" class=\"code\" alt><br>↑<a href=\"http://bgm.tv/subject/847\" target=\"_blank\" rel=\"nofollow external noopener\" class=\"l\">ハチミツとクローバー</a> ep.13↑<br><img src=\"http://r.loli.io/FzAZZj.jpg\" class=\"code\" alt><br><img src=\"http://r.loli.io/2miQvy.jpg\" class=\"code\" alt><br><img src=\"http://r.loli.io/7FVjqi.jpg\" class=\"code\" alt><br><img src=\"http://r.loli.io/va67Vn.jpg\" class=\"code\" alt><br><img src=\"http://r.loli.io/Y7vu63.jpg\" class=\"code\" alt><br><img src=\"http://r.loli.io/vUjeim.jpg\" class=\"code\" alt><br><img src=\"http://r.loli.io/VJRnMv.jpg\" class=\"code\" alt><br><img src=\"http://r.loli.io/iueyyi.jpg\" class=\"code\" alt><br>↑ハチミツとクローバー ep.24↑<br><img src=\"http://r.loli.io/E7bU7v.jpg\" class=\"code\" alt><br><img src=\"http://r.loli.io/3iQnie.jpg\" class=\"code\" alt><br><img src=\"http://r.loli.io/B7VvMz.jpg\" class=\"code\" alt><br><img src=\"http://r.loli.io/baaIbm.jpg\" class=\"code\" alt><br><img src=\"http://r.loli.io/FZzIbu.jpg\" class=\"code\" alt><br><img src=\"http://r.loli.io/mMfuMb.jpg\" class=\"code\" alt><br><img src=\"http://r.loli.io/MFRJJv.jpg\" class=\"code\" alt><br><img src=\"http://r.loli.io/6RFJRr.jpg\" class=\"code\" alt><br><img src=\"http://r.loli.io/iY77Vr.jpg\" class=\"code\" alt><br>↑<a href=\"http://bgm.tv/subject/37785\" target=\"_blank\" rel=\"nofollow external noopener\" class=\"l\">新世界より</a> ED1↑<br><img src=\"http://r.loli.io/iENZ3y.jpg\" class=\"code\" alt><br>↑新世界より ep.16↑<br><img src=\"http://r.loli.io/iYr6Zr.jpg\" class=\"code\" alt><br><img src=\"http://r.loli.io/JB7b2m.jpg\" class=\"code\" alt><br><img src=\"http://r.loli.io/juaYz2.jpg\" class=\"code\" alt><br><img src=\"http://r.loli.io/aeUFBr.jpg\" class=\"code\" alt><br><img src=\"http://r.loli.io/jUBZZ3.jpg\" class=\"code\" alt><br>↑新世界より ep.18↑<br><img src=\"http://r.loli.io/JB7bmy.jpg\" class=\"code\" alt><br><img src=\"http://r.loli.io/ryauYf.jpg\" class=\"code\" alt><br>↑<a href=\"http://bgm.tv/subject/896\" target=\"_blank\" rel=\"nofollow external noopener\" class=\"l\">ひだまりスケッチ</a> ep.2↑<br><img src=\"http://r.loli.io/ZVni22.jpg\" class=\"code\" alt><br><img src=\"http://r.loli.io/2eEFvq.jpg\" class=\"code\" alt><br>↑<a href=\"http://bgm.tv/subject/4235\" target=\"_blank\" rel=\"nofollow external noopener\" class=\"l\">かみちゅ!</a> ep.7↑<br><img src=\"http://1.loli.io/RFZZjm.jpg\" class=\"code\" alt><br>↑<a href=\"http://bgm.tv/subject/18082\" target=\"_blank\" rel=\"nofollow external noopener\" class=\"l\">ギャラクシーエンジェルAA</a> ep.37↑<br><img src=\"http://1.loli.io/FZjiem.jpg\" class=\"code\" alt><br>↑<a href=\"http://bgm.tv/subject/18083\" target=\"_blank\" rel=\"nofollow external noopener\" class=\"l\">ギャラクシーエンジェルX</a> ep.4↑<br><img src=\"http://1.loli.io/qUrUF3.jpg\" class=\"code\" alt><br>↑<a href=\"http://bgm.tv/subject/26449.jpg\" target=\"_blank\" rel=\"nofollow external noopener\" class=\"l\">人間さんの、じゃくにくきょうしょく</a> #5↑<br><img src=\"http://r.loli.io/aYFjIv.jpg\" class=\"code\" alt><br><img src=\"http://r.loli.io/Rbyiyy.jpg\" class=\"code\" alt><br>↑<a href=\"http://bgm.tv/subject/1938\" target=\"_blank\" rel=\"nofollow external noopener\" class=\"l\">スチームボーイ</a>↑<br><img src=\"http://1.loli.io/INv2aq.jpg\" class=\"code\" alt><br><img src=\"http://1.loli.io/MVZ3ea.jpg\" class=\"code\" alt><br><img src=\"http://1.loli.io/Uz6Rby.jpg\" class=\"code\" alt><br>↑<a href=\"http://bgm.tv/subject/58646\" target=\"_blank\" rel=\"nofollow external noopener\" class=\"l\">魔女っこ姉妹のヨヨとネネ</a>↑<br><img src=\"http://1.loli.io/AFzE3i.jpg\" class=\"code\" alt><br><img src=\"http://1.loli.io/uYfMFv.jpg\" class=\"code\" alt><br><img src=\"http://1.loli.io/fyaMfi.jpg\" class=\"code\" alt><br>↑<a href=\"http://bgm.tv/person/3080\" target=\"_blank\" rel=\"nofollow external noopener\" class=\"l\">Avex Entertainment</a>↑<br><img src=\"http://r.loli.io/NBJ7za.jpg\" class=\"code\" alt><br><img src=\"http://r.loli.io/QZn6ze.jpg\" class=\"code\" alt><br>↑<a href=\"http://bgm.tv/subject/3275\" target=\"_blank\" rel=\"nofollow external noopener\" class=\"l\">Avatar:The Last Airbender Season 1</a> ep.16↑<br><img src=\"http://r.loli.io/euyMbq.jpg\" class=\"code\" alt><br>↑<a href=\"http://bgm.tv/subject/4607\" target=\"_blank\" rel=\"nofollow external noopener\" class=\"l\">Avatar: The Last Airbender Season 2</a> ep.5↑<br><img src=\"http://r.loli.io/VFF3Ij.jpg\" class=\"code\" alt><br><img src=\"http://r.loli.io/iaAZfm.jpg\" class=\"code\" alt><br><img src=\"http://r.loli.io/nqAVJj.jpg\" class=\"code\" alt><br>↑<a href=\"http://bgm.tv/person/6816\" target=\"_blank\" rel=\"nofollow external noopener\" class=\"l\">Walt Disney Pictures</a>↑<br></p> ","time":"2014-6-30 20:44","title":"[EP1] [120P] 焰火 / 烟火 / 烟花 / 花火 / Hanabi / Fireworks","userId":"killy","userName":"Killy","userSign":"(被高空抛物的碎片弹到脸，可怕)"}