{"id":4921,"avatar":"//lain.bgm.tv/pic/user/m/000/00/93/9302.jpg","floor":"#1","group":"少年同盟","groupHref":"/group/kimitoboku","groupThumb":"//lain.bgm.tv/pic/icon/m/000/00/04/488.jpg?r=1310197360","message":"在最新一号的4月号「月刊G Fantasy」上，突然宣布了一个非常好的消息，那就是由漫画家堀田贵一所创作的作品「少年同盟」TV动画化决定了。简单来说，就如同名字所说，「少年同盟」是一部有关几名正处于青春期的少年的轻松搞笑学园故事。自少便认识的四位少年，有冷酷的双胞胎哥哥浅羽悠太、脱线的双胞胎弟弟浅羽佑希、学年首位的优等生班长冢原要、长著一张女生脸，个性温和的松冈春，这4名少年自少便组成一个属于他们的圈子，常常也因为一些很小或常给人忽略的不重要事而认真起来，是一部给人一种很轻松的搞笑作品。在这四人少年圈子中，再加上半日混血儿的转校生橘千鹤及算是本作女主角(这作品有女主角吗?)的佐藤茉咲，一起展开著充满青春的校园生活。<br><br>　　虽然本作的主要角色有很多都是男生，但本作絶不是BL向，而透过作者清淡的画风，故事以优闲的歩调进行著，再加上作者相当有意思的剧情安排，透过小事情来唤醒读者的回忆，营造出了非常出色的感情渲染，所以说是风格很像少女漫画的少年漫画了。「少年同盟」自04年连载开始至今便已推出了9卷漫画单行本，而且在早前更推出了超级出力的DRAMA CD，期声优阵容有「网球王子」的皆川纯子、甲斐田雪及森久保祥太郎，钢练的朴璐美及钉宫理恵，还有斉藤千和及竹内顺子等。如今的TV动画化可谓是很多人一直在期待，若果DRAMA CD声容能够沿用至TV动画里，真的会使很多人感动落泪。期待「少年同盟」TV动画的后续报导。<br><img src=\"http://www.dm123.cn/ecms/d/file/2011-03-16/bfd52d46cd122e2e482f6159cdc705cf.jpg\" class=\"code\" alt><br><a href=\"http://www.dm123.cn/new/xf/2011-03-16/32375.html\" target=\"_blank\" rel=\"nofollow external noopener\" class=\"l\">http://www.dm123.cn/new/xf/2011-03-16/32375.html</a><br>作者:hautecc   来自:动漫FANS新闻组<br><br>期待早些看到啊 ","time":"2011-3-21 16:28","title":"转：「少年同盟」TV动画化决定（3月16号的，可能有些晚了","userId":"youyue","userName":"utt","userSign":""}