{"id":373999,"avatar":"//lain.bgm.tv/pic/user/m/000/58/15/581555.jpg","floor":"#1","group":"靠谱人生茶话会","groupHref":"/group/boring","groupThumb":"//lain.bgm.tv/pic/icon/m/000/00/03/364.jpg","message":"<img src=\"https://p.sda1.dev/7/c1260206ef26c95dfd187489930ad070/1_LI.jpg\" class=\"code\" rel=\"noreferrer\" referrerpolicy=\"no-referrer\" alt><br>今天逛IT之家偶然看见的<br>但是去豆瓣一看压根也没显示，明显是豆瓣，但不是一个界面，图片里还能看到imdb和mal的分数<br><br><img src=\"https://p.sda1.dev/7/47f3ea65534d12ec8413782a82fe2e00/2.jpg\" class=\"code\" rel=\"noreferrer\" referrerpolicy=\"no-referrer\" alt><br>这个是正常豆瓣赛博朋客的界面 ","time":"2022-10-19 13:24","title":"豆瓣上这个BGM top 250的标是在哪里找到的","userId":"581555","userName":"Michen","userSign":"(bgm评分体系崩塌吹哨人)"}