{"avatar":"//lain.bgm.tv/pic/user/m/000/41/00/410042.jpg","floor":"#1","group":"靠谱人生茶话会","groupHref":"/group/boring","groupThumb":"//lain.bgm.tv/pic/icon/m/000/00/03/364.jpg","message":"15年入的bangumi 当了4年的伸手党最后才发现锁了数据库的访问权限，今天又无意间发现跟爱弹幕一样只是隐藏了tag的地址，除了封面其他人物和导演什么都还能看，有的好像还是不能浏览，不知道是手机端还是权限的问题，能有点是一点吧，抽时间做个脚本不然 li番没封面真的是很难受<img src=\"http://wx4.sinaimg.cn/thumb180/b32444a9ly1fpjoxk1iqtj20qo1ben43.jpg\" class=\"code\" alt><img src=\"http://wx3.sinaimg.cn/thumb180/b32444a9ly1fpjoxj78rrj20qo1bednf.jpg\" class=\"code\" alt> ","time":"2018-3-20 19:49","title":"游客状态查看li番tag","userId":"z1103758","userName":"喵ははは","userSign":"(深度yd废宅)"}