{"id":384503,"avatar":"//lain.bgm.tv/pic/user/m/000/35/13/351390.jpg","floor":"#1","group":"不靠谱人生茶话会","groupHref":"/group/bored","groupThumb":"//lain.bgm.tv/pic/icon/m/000/00/44/4409.jpg?r=1596816273","message":"————————————————————————————————————————————<br><br>那年，我妈是我们学校的某主任。<br><br><span style=\"font-size:25px; line-height:25px;\">一：</span><br><br>虽然在同一个学校，但是她每天下班都很晚，所以平时放学，我都是等我爸来接我的。<br>某日，我在校门口苦等许久，老爸都没有来，这个时候，我们班的数学老师走了过来。<br><br>“怎么这么晚了还不回家？你家住哪里？老师有车跟老师一起走吧！”<br><br>我并没有多想，觉得数学老师也不是坏人，我早就想吃晚饭了，早点回去未尝不可。<br><br>然而坐老师的车回到家后，却被她质问我怎么回来的。<br>我被这突如其来的质问给吓住了，只道是学校老师送我回来的。我妈并未再追究，买了一箱牛奶，让我明天给老师带去。<br><br>“明天放学送到她车里，别欠老师人情。”她嘱咐到。<br><br>————————————————————————————————————————————<br><br><span style=\"font-size:25px; line-height:25px;\">二：</span><br><br>那年，市里有作文竞赛，我平时语文偶尔冲个高分，基本只在中上水平。那次评选，我却破天荒地成为少数几个幸运儿代表学校参加竞赛。<br><br>我很开心，觉得这一切都是老师对我实力的认可。然而当我将这一切和我妈说的时候，她回复却很冷淡。只是让我好好加油，再接再厉。她并没有表现出欣喜的神态，好像是早就预料到了。<br><br>就在那年暑假，她给我买了几本语文教辅，拼命让我练习写作，即便只有3年级，我却要尝试500字的长文撰写，由她批改。<br><br>“加油，我相信你，你要让他们知道你的作文获选是因为你自己的实力，而不是靠人情。”她这么鼓励我。<br><br>————————————————————————————————————————————<br><br>若干年后再次提起这几件事，我妈给了我全面的解答，并将这一切当作是人情世故的案例分析给我听。<br><br>一：<br>       她是主任，对老师的升迁评优评选有着举足轻重的作用。<br>       自然各个老师都想着办法巴结我妈。假如接送我的那个数学老师没被选上优秀教师开始抱怨，我妈则可能遭人诟病。<br>       她便购置了一箱牛奶让我送给数学老师，就当作是送我回家这件事的回礼了，两不相欠。<br><br>二：<br>       我的作文被选上参加竞赛，这件事里，其实我的实力并不重要。很可能在多方因素的干预下，这是必然事件。<br>       又是害怕遭人诟病的原因，我妈便强力提升我的语文，希望我用自身的实力来堵住那些质疑我德不配位的人的嘴。<br><br>————————————————————————————————————————————<br>      <br>“其实说真的，有必要么？这些都是小事，没必要这么敏感，你和她同事一场，她送我回家在情理之中。”我这么回复我妈。<br><br>“有必要，不得不做，不管怎么样别欠人情，等你步入职场就懂了。”她说。 ","time":"2023-7-19 20:02","title":"别欠他人情","userId":"lostpig","userName":"𝙇𝙤𝙨𝙩 𝙋𝙞𝙜 🎉","userSign":"(被遗忘的小猪会被遗忘吗？)"}