{"id":28566,"avatar":"//lain.bgm.tv/pic/user/m/000/03/15/31568.jpg","floor":"#1","group":"胡思乱想团","groupHref":"/group/husiluanxiang","groupThumb":"//lain.bgm.tv/pic/icon/m/000/00/07/729.jpg?r=1306292725","message":"我每到一个城市就会换一个身份。<br>这个不可思议的事情发生在我第一次离开自己生活了18年的城市，坐火车去杭州。<br>那是我中学毕业，只是想去周边的城市玩一下。<br>我完全没想到有人会来接我，一个中年妇女拥抱了我，叫我儿子。<br>本来是孤儿的我，一瞬间以为是孤儿院的院长安排的这一切。<br>我说起要利用打工赚的钱旅行的时候，他建议我来这里的。<br>但是我在簇拥中坐上回家的出租车时，身边自称是我妹妹的人拿出来自称是我打电话叫她带给我的可口可乐。<br>他们一定不是第一次见我，完全没有生疏的样子。<br>我当时很庆幸——这显然是一个误会——虽然这种事应该不会误会。<br>但是我想或许老天都亏欠一个家庭对我18年了，所以现在回报了我一下，我享受就是了。<br>于是我冒充了一个参军探亲的儿子，享受了7天；各种惊险中，我还是没有露馅。<br><br>两个星期后，我去了上海上大学。<br>陌生的同学主动上来叫我“陈宇”，我不认识他，也不知道“陈宇”是谁。<br>他问我要不要周末一起回家，说“想你陪我去拍演唱会的门票，是你也喜欢的五月天”。<br>我知道五月天，但是我不知道我原来喜欢他们。<br>我想误会不能一次次地发生在我身上。<br>我想我遇到了不可思议的事情。<br>我觉得这件事太好玩了！<br>如果你的生命中原本是一潭死水，那么点滴涟漪也会叫惊喜，更何况是惊涛骇浪。<br>我答应了他，然后周末我来到了另一个家庭，有了另一个叫我儿子的妈妈。<br>我有了一群发小，我打了据说我最喜欢的篮球，被他们斥责退步地不像样子。<br>我去听了五月天的音乐会，还有女孩子含情脉脉地看着我，当他们唱道“突然好想你”。<br>我不知道其中的故事，但是我知道应该有故事的。<br><br>我思考过很多原因，为什么会发生这样的事情。<br>我思考得更多是，怎么样才会发生这样的事情。<br>原因一：没有原因，不知道什么时候就会发生这样不可思议的事情。<br>原因二：我成年了，某种冥冥中的神秘力量启动了。<br>原因三：我换了城市，换了身份。<br>我自己很倾心第三种原因，所以我又去了一下外地——苏州。<br>我在站台上没有看到亲人，些许失望。<br>我在这个陌生的城里随意走，路过一个中学，就不由自主地停下来向里面张望。<br>一个老师样子的人突然出现了，她向我微笑，对着我叫了一个陌生的名字。<br>果然我的猜测有可能是正确的，我到了新的城市就换了新的身份。<br>她很有班主任风范地询问我大学生活如何，怎么这么快回家。<br>我怀着对母亲的爱恋之情，和她走了一会路，说了一些话。<br>于是我知道我在这里的身份是去了英国留学的好孩子，出去还没有两个月，所以这时回来些许有些奇怪。<br>可惜她没有透露我在这座城市的家在哪里。<br>我围着学校转，周边的小区里进进出出的人，都当我是陌生人。<br>我想或许我在某个城市只有一部分人或几个人或一个人认识我。<br><br>我每到一个城市就会换一个身份。<br>是不是很奇妙。 ","time":"2013-9-30 13:55","title":"我每到一个城市就会换一个身份","userId":"haohao69","userName":"好好","userSign":""}