{"id":5539,"avatar":"//lain.bgm.tv/pic/user/m/000/03/04/30429.jpg","floor":"#1","group":"etokei 绘时计","groupHref":"/group/etokei","groupThumb":"//lain.bgm.tv/pic/icon/m/000/00/05/511.jpg","message":"<img src=\"http://bgm.tv/pic/tokei/m/f5/23/1377_x0in7.jpg\" class=\"code\" alt><br><a href=\"http://bgm.tv/tokei/paint/1377\" target=\"_blank\" rel=\"nofollow external noopener\" class=\"l\">http://bgm.tv/tokei/paint/1377</a> by <a href=\"http://bgm.tv/user/memekoanxii\" target=\"_blank\" rel=\"nofollow external noopener\" class=\"l\">Anxii</a> ","time":"2011-5-7 20:35","title":"「20:21」by Anxii","userId":"memekoanxii","userName":"Anxii","userSign":"(magic☆变身！)"}