{"id":31325,"avatar":"//lain.bgm.tv/pic/user/m/000/15/58/155897.jpg","floor":"#1","group":"天窗联盟 - 寄卖、合摊宣传版","groupHref":"/group/consign","groupThumb":"//lain.bgm.tv/pic/icon/m/000/00/08/822.jpg?r=1311077169","message":"已经申请3月23日古剑奇谭，4月19日剑三ONLY，5月1~3萤火虫动漫嘉年华，如果本子足够会申请同期的YACA展，原3月剑三改期到5月也是申请通过的。<br>除了广州之外偶尔会跑佛山，深圳，珠海的展。<br>如果寄售的是本子最好能有代理权能给申请摊位的，这样会参加港澳，上海，杭州的展，主要看时间。<br>通常情况下一个展子结束后1~2日结数，如果特殊情况，2个展相差时间不大，例如1月1日的 展子结束1月3还有一个这样日期距离相近的展，即全部结束完才能结。<br>可以交换寄售，我的商品都是些周边类，可以交换寄售。<br>寄售费用：本子10%，周边15%<br>请敲QQ1908975094（注：寄卖） ","time":"2014-3-3 14:42","title":"【个人】【广州】接寄卖长期参展3月古剑4月剑三5月萤火虫已经通过审核","userId":"155897","userName":"月梦璃","userSign":"(得不到的无须强求)"}