[{"id":4923,"uid":"infinte","un":"infinte","av":"000/00/82/8284","t":"超展开列表 AJAX 刷新 功能请求","ti":"2011-3-21 19:30","g":"站务论坛","gh":"forum"},{"id":4562,"uid":"infinte","un":"infinte","av":"000/00/82/8284","t":"提醒的建议","ti":"2011-2-17 20:36","g":"站务论坛","gh":"forum"},{"id":4561,"uid":"infinte","un":"infinte","av":"000/00/82/8284","t":"做下单点登录好么？","ti":"2011-2-17 20:15","g":"站务论坛","gh":"forum"},{"id":4524,"uid":"infinte","un":"infinte","av":"000/00/82/8284","t":"导航栏的建议","ti":"2011-2-12 00:00","g":"站务论坛","gh":"forum"},{"id":4462,"uid":"infinte","un":"infinte","av":"000/00/82/8284","t":"超展开左边的列表","ti":"2011-2-2 00:28","g":"站务论坛","gh":"forum"}]