{"id":23340,"avatar":"//lain.bgm.tv/pic/user/m/000/01/43/14382.jpg","floor":"#1","group":"愛撕衣的后花園","groupHref":"/group/saraba1st","groupThumb":"//lain.bgm.tv/pic/icon/m/000/00/00/28.jpg","message":"<a href=\"http://220.196.42.172/2b/read-htm-tid-915524.html\" target=\"_blank\" rel=\"nofollow external noopener\" class=\"l\">即日起清理一切体制、国内政体、非官方群体事件、疑似政治的内容 - snoopys</a><br><br><a href=\"http://220.196.42.172/2b/hack.php?H_name=jail\" target=\"_blank\" rel=\"nofollow external noopener\" class=\"l\">小黑屋</a><div class=\"quote\"><q>被塞纱布：md2000<br>抹布原因：你们<br>>>>>>>>：违规言论        <br>抹布时间：2013-05-06 20:59<br>剩余时间：等不到这天<br>行刑版主：兲蛋高达 </q></div>液！ ","time":"2013-5-7 09:41","title":"域名就快做完了，我先删完号再开放，即日即时开始(2013-05-06)","userId":"laoism","userName":"林卯","userSign":"(✨️VIP 8✨️)"}