{"id":414166,"avatar":"//lain.bgm.tv/pic/user/m/000/38/18/381840.jpg","floor":"#1","group":"补旧番","groupHref":"/group/fillgrids","groupThumb":"//lain.bgm.tv/pic/icon/m/000/00/06/651.jpg","message":"过来人经验。前两天补了药屋少女第一季，算是芙莉莲之后又一个让我 没有一秒钟感到无聊的动画。我就2-3天时间看完了整个第一季。现在无比空虚，干正事没有动力。<br>反省，在过去活着的30年，我可能在看动画里花了半年到一年时间。特别是早期看动画时，仿佛打开新世界，一有时间就是一天一部，心理测量者 寒蝉 这种超好看的，更是马拉松式地看，遇到一个喜欢的导演，就追着作品一星期看完之类的。现在，动画生产没落下，但觉得有趣的越来越少，自己阈值提高，不靠饭就看不下去。偶尔遇到好看的，真是感天动地。<br>这就是一冲到底的后果，把好看的，均匀地分布在人生中去看，才是明智的做法。而且，好看的动画能作为你干正事努力后的奖励，成为有益的激励。没有努力和等待就能看动画？唔像是瘾君子，自毁大脑。","time":"2025-1-14 15:33","title":"遇到好看的动画，不要一口气","userId":"wakakap","userName":"wakaka","userSign":""}