{"id":403350,"avatar":"//lain.bgm.tv/pic/user/m/000/06/34/63429.jpg","floor":"#1","group":"补旧番","groupHref":"/group/fillgrids","groupThumb":"//lain.bgm.tv/pic/icon/m/000/00/06/651.jpg","message":"除非双方是真的撕破脸互殴打斗（有深仇大恨那种），否则我是真的受不了ACG作品里因男女角色日常相处的破事就啪的一巴掌打过去的行为，这不叫表现激烈情绪，这就是肢体暴力，被打的一方完全可以直接还手也不需要顾虑什么。<br><br>对方都一言不合直接动手了，那为什么还要“照顾对方感受”？合着就许对方打人发泄情绪，被打一方就得受着？这就是完全没道理的。（但是ACG作品里此类情况下，常常出现被打者懵逼一瞬间然后就开始给对方找理由.....）<br><br>要我说别管对方是男是女了，日常相处时候诉诸暴力的一方就是垃圾，被打者不该惯毛病，就应该直接反手一巴掌糊脸过去——如果对方还想打那就继续，反正到这时候就是互相不给脸了，大不了都挨个治安处分。<br><br>哦你说确立恋爱关系后男女方也有这种事？那这时候所谓“家暴”概念敢不敢别限定在某一性别？谁先动手谁就是施暴者，就活该被另一方反击然后一脚给踹了。<br><br>但是这么多年来无数的ACG作品对男女相处时候的暴力行为都有意淡化危害性甚至娱乐化，似乎这还是一种“有趣的笑点”和“萌点”？我只能说主创人员是真的挺恶心的。","time":"2024-8-8 02:39","title":"越来越受不了男女相处时候的暴力行为，不论是恋爱关系还是同学/朋友关系","userId":"akb49","userName":"老白","userSign":"(Anime is trash and so am I.)"}