{"id":392000,"avatar":"//lain.bgm.tv/pic/user/m/000/30/20/302081.jpg","floor":"#1","group":"靠谱人生茶话会","groupHref":"/group/boring","groupThumb":"//lain.bgm.tv/pic/icon/m/000/00/03/364.jpg","message":"回顾2023，我去了不少地方，见了不少人，想明白了一些事情，秋招也找到工作了，总体来说目标实现了。展望2024，我的目标有：<br>1. 硕士毕业，善始善终，处理好一些人际关系，走完这个专业的求学路，如果还要继续学，肯定不会学电气了；<br>2. 再学习一些CS知识，虽然暂时不知道学了要做什么；<br>3. 继续学电吉他，现在还是太菜了，希望能弹些喜欢的金属；<br>4. 完成学生到社会人的转变，看看自己是否能适应这个所谓的归宿企业。我在求职时已经做了会让99%的人满意的选择，如果我对此仍不满意，只能说明我不适合这个行业，不论如何都应该离开。","time":"2024-1-2 17:44","title":"你们2024年的目标是什么","userId":"dopamine","userName":"DB","userSign":"(不太想活的人)"}