[{"avatar":"//lain.bgm.tv/pic/user/m/000/07/84/78408.jpg","floor":"#2","id":"1254322","time":"2017-6-24 00:10","userId":"amyhabor","userName":"琴吹七瀨","userSign":"(女儿是父亲上辈子的情人，不跟女儿H的都是异端 ... ... ...)","message":"<a href=\"/user/chu2otaku\" class=\"l\">@＠chu2story</a><a href=\"/user/conan\" class=\"l\">@滾滾洗衣君</a><a href=\"/user/zodiacg\" class=\"l\">@zodiacg</a><a href=\"/user/chooperchang\" class=\"l\">@海卫四</a><a href=\"/user/dronce\" class=\"l\">@宇佐美 度</a><a href=\"/user/w\" class=\"l\">@如月千早</a><a href=\"/user/insulsa\" class=\"l\">@把友情留在无盐</a><a href=\"/user/nenu_xlp\" class=\"l\">@夏蓝谱</a><a href=\"/user/detao0452\" class=\"l\">@Detao</a>","sub":[]},{"avatar":"//lain.bgm.tv/pic/user/m/000/07/84/78408.jpg","floor":"#3","id":"1254323","time":"2017-6-24 00:11","userId":"amyhabor","userName":"琴吹七瀨","userSign":"(女儿是父亲上辈子的情人，不跟女儿H的都是异端 ... ... ...)","message":"<a href=\"/user/amyhabor\" class=\"l\">@琴吹七瀨</a><a href=\"/user/72935\" class=\"l\">@出戏</a><a href=\"/user/bunny1ov3r\" class=\"l\">@用生命开后宫的男人</a><a href=\"/user/magicat\" class=\"l\">@猫乃魔物</a><a href=\"/user/ichimatsu\" class=\"l\">@松野一松</a><a href=\"/user/upsuper\" class=\"l\">@upsuper</a><a href=\"/user/26866\" class=\"l\">@月火</a><a href=\"/user/basertyu\" class=\"l\">@basertyu(流氓豆)</a><a href=\"/user/322236\" class=\"l\">@StrawberryKing</a>","sub":[]},{"avatar":"//lain.bgm.tv/pic/user/m/000/07/84/78408.jpg","floor":"#4","id":"1254325","time":"2017-6-24 00:13","userId":"amyhabor","userName":"琴吹七瀨","userSign":"(女儿是父亲上辈子的情人，不跟女儿H的都是异端 ... ... ...)","message":"擂台 01: 牧濑红莉栖        [td]-[/td]        <span style=\"color: #0000DF;\"><span style=\"font-weight:bold;\">[平泽唯]</span></span><br>擂台 02: 萝莉·麦丘利        [td]-[/td]        <span style=\"color: #0000DF;\"><span style=\"font-weight:bold;\">[阿库娅]</span></span><br>擂台 03: 楪祈        <span style=\"color: #FF0000;\"><span style=\"font-weight:bold;\">[弃权]</span></span>        小爱<br>擂台 04: 逢坂大河        <span style=\"color: #FF0000;\"><span style=\"font-weight:bold;\">[弃权]</span></span>        忍野忍<br>擂台 05: <span style=\"color: #0000DF;\"><span style=\"font-weight:bold;\">[白石丽]</span></span>        [td]-[/td]        宫水三叶<br>擂台 06: 金色暗影        <span style=\"color: #FF0000;\"><span style=\"font-weight:bold;\">[弃权]</span></span>        赫斯缇雅<br>擂台 07: 四糸乃        <span style=\"color: #FF0000;\"><span style=\"font-weight:bold;\">[弃权]</span></span>        晓美焰<br>擂台 08: <span style=\"color: #0000DF;\"><span style=\"font-weight:bold;\">[宇佐美瑞希]</span></span>        [td]-[/td]        小鸟游六花<br>擂台 09: 宫园薰        <span style=\"color: #FF0000;\"><span style=\"font-weight:bold;\">[弃权]</span></span>        羽川翼<br>擂台 10: 小野寺小咲        <span style=\"color: #FF0000;\"><span style=\"font-weight:bold;\">[弃权]</span></span>        C.C.<br>擂台 11: 木之本樱        [td]-[/td]        <span style=\"color: #0000DF;\"><span style=\"font-weight:bold;\">[吉普莉尔]</span></span><br>擂台 12: 古河渚        <span style=\"color: #FF0000;\"><span style=\"font-weight:bold;\">[弃权]</span></span>        间桐樱<br>擂台 13: 我妻由乃        <span style=\"color: #FF0000;\"><span style=\"font-weight:bold;\">[弃权]</span></span>        食蜂操祈<br>擂台 14: 椎名真白        [td]-[/td]        <span style=\"color: #0000DF;\"><span style=\"font-weight:bold;\">[凉风青叶]</span></span><br>擂台 15: <span style=\"color: #0000DF;\"><span style=\"font-weight:bold;\">[泷本日富美]</span></span>        [td]-[/td]        霞之丘诗羽<br>擂台 16: <span style=\"color: #0000DF;\"><span style=\"font-weight:bold;\">[潮田渚]</span></span>        [td]-[/td]        平和岛静雄<br>擂台 17: 哈尔希洛        <span style=\"color: #FF0000;\"><span style=\"font-weight:bold;\">[弃权]</span></span>        菜月昴<br>擂台 18: 绫崎飒        <span style=\"color: #FF0000;\"><span style=\"font-weight:bold;\">[弃权]</span></span>        太宰治<br>擂台 19: 卫宫士郎        <span style=\"color: #FF0000;\"><span style=\"font-weight:bold;\">[弃权]</span></span>        贝尔·克朗尼<br>擂台 20: 日向创        <span style=\"color: #FF0000;\"><span style=\"font-weight:bold;\">[弃权]</span></span>        坂本<br>擂台 21: 折原临也        <span style=\"color: #FF0000;\"><span style=\"font-weight:bold;\">[弃权]</span></span>        卡米那<br>擂台 22: <span style=\"color: #0000DF;\"><span style=\"font-weight:bold;\">[菲利克斯·阿盖尔]</span></span>        [td]-[/td]        野崎梅太郎<br>擂台 23: 御狐神双炽        <span style=\"color: #FF0000;\"><span style=\"font-weight:bold;\">[弃权]</span></span>        阿良良木历<br>擂台 24: 有马公生        <span style=\"color: #FF0000;\"><span style=\"font-weight:bold;\">[弃权]</span></span>        伊丹耀司<br>擂台 25: 夜斗        [td]-[/td]        <span style=\"color: #0000DF;\"><span style=\"font-weight:bold;\">[土间太平]</span></span><br>擂台 26: 天雾绫斗        <span style=\"color: #FF0000;\"><span style=\"font-weight:bold;\">[弃权]</span></span>        高须龙儿<br>擂台 27: L Lawliet        [td]-[/td]        <span style=\"color: #0000DF;\"><span style=\"font-weight:bold;\">[晓古城]</span></span><br>擂台 28: 影山飞雄        [td]-[/td]        <span style=\"color: #0000DF;\"><span style=\"font-weight:bold;\">[安兹·乌尔·恭]</span></span><br>擂台 29: 比企谷八幡        <span style=\"color: #FF0000;\"><span style=\"font-weight:bold;\">[弃权]</span></span>        真奥贞夫<br>擂台 30: 內卷昴        [td]-[/td]        <span style=\"color: #0000DF;\"><span style=\"font-weight:bold;\">[Lancer]</span></span><br>擂台 31: 克劳恩皮丝        <span style=\"color: #FF0000;\"><span style=\"font-weight:bold;\">[弃权]</span></span>        水桥帕露希<br>擂台 32: 八云蓝        <span style=\"color: #FF0000;\"><span style=\"font-weight:bold;\">[弃权]</span></span>        洩矢諏访子","sub":[]},{"avatar":"//lain.bgm.tv/pic/user/m/000/17/59/175982.jpg","floor":"#5","id":"1254327","time":"2017-6-24 00:27","userId":"chu2otaku","userName":"原来的头像呢","userSign":"(null)","message":"擂台 01: 牧濑红莉栖        [td]-[/td]        <span style=\"color: #0000DF;\"><span style=\"font-weight:bold;\">[平泽唯]</span></span><br>擂台 02: 萝莉·麦丘利        <span style=\"color: #FF0000;\"><span style=\"font-weight:bold;\">[弃权]</span></span>        阿库娅<br>擂台 03: <span style=\"color: #0000DF;\"><span style=\"font-weight:bold;\">[楪祈]</span></span>        [td]-[/td]        小爱<br>擂台 04: <span style=\"color: #0000DF;\"><span style=\"font-weight:bold;\">[逢坂大河]</span></span>        [td]-[/td]        忍野忍<br>擂台 05: 白石丽        [td]-[/td]        <span style=\"color: #0000DF;\"><span style=\"font-weight:bold;\">[宫水三叶]</span></span><br>擂台 06: 金色暗影        <span style=\"color: #FF0000;\"><span style=\"font-weight:bold;\">[弃权]</span></span>        赫斯缇雅<br>擂台 07: 四糸乃        [td]-[/td]        <span style=\"color: #0000DF;\"><span style=\"font-weight:bold;\">[晓美焰]</span></span><br>擂台 08: 宇佐美瑞希        [td]-[/td]        <span style=\"color: #0000DF;\"><span style=\"font-weight:bold;\">[小鸟游六花]</span></span><br>擂台 09: 宫园薰        [td]-[/td]        <span style=\"color: #0000DF;\"><span style=\"font-weight:bold;\">[羽川翼]</span></span><br>擂台 10: 小野寺小咲        [td]-[/td]        <span style=\"color: #0000DF;\"><span style=\"font-weight:bold;\">[C.C.]</span></span><br>擂台 11: <span style=\"color: #0000DF;\"><span style=\"font-weight:bold;\">[木之本樱]</span></span>        [td]-[/td]        吉普莉尔<br>擂台 12: <span style=\"color: #0000DF;\"><span style=\"font-weight:bold;\">[古河渚]</span></span>        [td]-[/td]        间桐樱<br>擂台 13: 我妻由乃        [td]-[/td]        <span style=\"color: #0000DF;\"><span style=\"font-weight:bold;\">[食蜂操祈]</span></span><br>擂台 14: <span style=\"color: #0000DF;\"><span style=\"font-weight:bold;\">[椎名真白]</span></span>        [td]-[/td]        凉风青叶<br>擂台 15: <span style=\"color: #0000DF;\"><span style=\"font-weight:bold;\">[泷本日富美]</span></span>        [td]-[/td]        霞之丘诗羽<br>擂台 16: 潮田渚        <span style=\"color: #FF0000;\"><span style=\"font-weight:bold;\">[弃权]</span></span>        平和岛静雄<br>擂台 17: 哈尔希洛        <span style=\"color: #FF0000;\"><span style=\"font-weight:bold;\">[弃权]</span></span>        菜月昴<br>擂台 18: <span style=\"color: #0000DF;\"><span style=\"font-weight:bold;\">[绫崎飒]</span></span>        [td]-[/td]        太宰治<br>擂台 19: 卫宫士郎        <span style=\"color: #FF0000;\"><span style=\"font-weight:bold;\">[弃权]</span></span>        贝尔·克朗尼<br>擂台 20: 日向创        <span style=\"color: #FF0000;\"><span style=\"font-weight:bold;\">[弃权]</span></span>        坂本<br>擂台 21: 折原临也        [td]-[/td]        <span style=\"color: #0000DF;\"><span style=\"font-weight:bold;\">[卡米那]</span></span><br>擂台 22: <span style=\"color: #0000DF;\"><span style=\"font-weight:bold;\">[菲利克斯·阿盖尔]</span></span>        [td]-[/td]        野崎梅太郎<br>擂台 23: 御狐神双炽        [td]-[/td]        <span style=\"color: #0000DF;\"><span style=\"font-weight:bold;\">[阿良良木历]</span></span><br>擂台 24: 有马公生        <span style=\"color: #FF0000;\"><span style=\"font-weight:bold;\">[弃权]</span></span>        伊丹耀司<br>擂台 25: 夜斗        <span style=\"color: #FF0000;\"><span style=\"font-weight:bold;\">[弃权]</span></span>        土间太平<br>擂台 26: 天雾绫斗        [td]-[/td]        <span style=\"color: #0000DF;\"><span style=\"font-weight:bold;\">[高须龙儿]</span></span><br>擂台 27: L Lawliet        <span style=\"color: #FF0000;\"><span style=\"font-weight:bold;\">[弃权]</span></span>        晓古城<br>擂台 28: 影山飞雄        <span style=\"color: #FF0000;\"><span style=\"font-weight:bold;\">[弃权]</span></span>        安兹·乌尔·恭<br>擂台 29: <span style=\"color: #0000DF;\"><span style=\"font-weight:bold;\">[比企谷八幡]</span></span>        [td]-[/td]        真奥贞夫<br>擂台 30: 內卷昴        <span style=\"color: #FF0000;\"><span style=\"font-weight:bold;\">[弃权]</span></span>        Lancer<br>擂台 31: 克劳恩皮丝        <span style=\"color: #FF0000;\"><span style=\"font-weight:bold;\">[弃权]</span></span>        水桥帕露希<br>擂台 32: <span style=\"color: #0000DF;\"><span style=\"font-weight:bold;\">[八云蓝]</span></span>        [td]-[/td]        洩矢諏访子<br><br>感谢召唤<br><br>什么时候红白和黑白来一场w","sub":[]},{"avatar":"//lain.bgm.tv/pic/user/m/000/26/78/267845.jpg","floor":"#6","id":"1254336","time":"2017-6-24 00:42","userId":"basertyu","userName":"小鸠世界第一可爱","userSign":"(noblesse oblige)","message":"ARENA 01: 牧瀬紅莉栖        [td]-[/td]        <span style=\"color: #0000DF;\"><span style=\"font-weight:bold;\">[平沢唯]</span></span><br>ARENA 02: ロゥリィ・マーキュリー        <span style=\"color: #FF0000;\"><span style=\"font-weight:bold;\">[棄権]</span></span>        アクア<br>ARENA 03: 楪いのり        <span style=\"color: #FF0000;\"><span style=\"font-weight:bold;\">[棄権]</span></span>        アイちゃん<br>ARENA 04: 逢坂大河        <span style=\"color: #FF0000;\"><span style=\"font-weight:bold;\">[棄権]</span></span>        忍野忍<br>ARENA 05: 白石うらら        <span style=\"color: #FF0000;\"><span style=\"font-weight:bold;\">[棄権]</span></span>        宮水三葉<br>ARENA 06: 金色の闇        <span style=\"color: #FF0000;\"><span style=\"font-weight:bold;\">[棄権]</span></span>        ヘスティア<br>ARENA 07: 四糸乃        <span style=\"color: #FF0000;\"><span style=\"font-weight:bold;\">[棄権]</span></span>        暁美ほむら<br>ARENA 08: 宇佐美みずき        <span style=\"color: #FF0000;\"><span style=\"font-weight:bold;\">[棄権]</span></span>        小鳥遊六花<br>ARENA 09: 宮園かをり        <span style=\"color: #FF0000;\"><span style=\"font-weight:bold;\">[棄権]</span></span>        羽川翼<br>ARENA 10: <span style=\"color: #0000DF;\"><span style=\"font-weight:bold;\">[小野寺小咲]</span></span>        [td]-[/td]        C.C.<br>ARENA 11: <span style=\"color: #0000DF;\"><span style=\"font-weight:bold;\">[木之本桜]</span></span>        [td]-[/td]        ジブリール<br>ARENA 12: <span style=\"color: #0000DF;\"><span style=\"font-weight:bold;\">[古河渚]</span></span>        [td]-[/td]        間桐桜<br>ARENA 13: 我妻由乃        <span style=\"color: #FF0000;\"><span style=\"font-weight:bold;\">[棄権]</span></span>        食蜂操祈<br>ARENA 14: 椎名ましろ        <span style=\"color: #FF0000;\"><span style=\"font-weight:bold;\">[棄権]</span></span>        涼風青葉<br>ARENA 15: 滝本ひふみ        <span style=\"color: #FF0000;\"><span style=\"font-weight:bold;\">[棄権]</span></span>        霞ヶ丘詩羽<br>ARENA 16: 潮田渚        [td]-[/td]        <span style=\"color: #0000DF;\"><span style=\"font-weight:bold;\">[平和島静雄]</span></span><br>ARENA 17: ハルヒロ        <span style=\"color: #FF0000;\"><span style=\"font-weight:bold;\">[棄権]</span></span>        菜月昴<br>ARENA 18: 綾崎ハヤテ        <span style=\"color: #FF0000;\"><span style=\"font-weight:bold;\">[棄権]</span></span>        太宰治<br>ARENA 19: 衛宮士郎        <span style=\"color: #FF0000;\"><span style=\"font-weight:bold;\">[棄権]</span></span>        ベル・クラネル<br>ARENA 20: 日向創        <span style=\"color: #FF0000;\"><span style=\"font-weight:bold;\">[棄権]</span></span>        坂本<br>ARENA 21: 折原臨也        <span style=\"color: #FF0000;\"><span style=\"font-weight:bold;\">[棄権]</span></span>        カミナ<br>ARENA 22: フェリックス・アーガイル        [td]-[/td]        <span style=\"color: #0000DF;\"><span style=\"font-weight:bold;\">[野崎梅太郎]</span></span><br>ARENA 23: 御狐神双熾        <span style=\"color: #FF0000;\"><span style=\"font-weight:bold;\">[棄権]</span></span>        阿良々木暦<br>ARENA 24: 有馬公生        <span style=\"color: #FF0000;\"><span style=\"font-weight:bold;\">[棄権]</span></span>        伊丹耀司<br>ARENA 25: 夜ト        <span style=\"color: #FF0000;\"><span style=\"font-weight:bold;\">[棄権]</span></span>        土間太平<br>ARENA 26: 天霧綾斗        <span style=\"color: #FF0000;\"><span style=\"font-weight:bold;\">[棄権]</span></span>        高須竜児<br>ARENA 27: <span style=\"color: #0000DF;\"><span style=\"font-weight:bold;\">[エル・ローライト]</span></span>        [td]-[/td]        暁古城<br>ARENA 28: 影山飛雄        <span style=\"color: #FF0000;\"><span style=\"font-weight:bold;\">[棄権]</span></span>        アインズ・ウール・ゴウン<br>ARENA 29: 比企谷八幡        [td]-[/td]        <span style=\"color: #0000DF;\"><span style=\"font-weight:bold;\">[真奥貞夫]</span></span><br>ARENA 30: 内巻すばる        <span style=\"color: #FF0000;\"><span style=\"font-weight:bold;\">[棄権]</span></span>        ランサー<br>ARENA 31: クラウンピース        <span style=\"color: #FF0000;\"><span style=\"font-weight:bold;\">[棄権]</span></span>        水橋パルスィ<br>ARENA 32: 八雲藍        <span style=\"color: #FF0000;\"><span style=\"font-weight:bold;\">[棄権]</span></span>        洩矢諏訪子","sub":[]},{"avatar":"//lain.bgm.tv/pic/user/m/000/12/77/127728.jpg","floor":"#7","id":"1254393","time":"2017-6-24 06:29","userId":"chooperchang","userName":"海卫四","userSign":"(不要停！)","message":"ARENA 01: <span style=\"color: #0000DF;\"><span style=\"font-weight:bold;\">[牧瀬紅莉栖]</span></span>        [td]-[/td]        平沢唯<br>ARENA 02: ロゥリィ・マーキュリー        [td]-[/td]        <span style=\"color: #0000DF;\"><span style=\"font-weight:bold;\">[アクア]</span></span><br>ARENA 03: <span style=\"color: #0000DF;\"><span style=\"font-weight:bold;\">[楪いのり]</span></span>        [td]-[/td]        アイちゃん<br>ARENA 04: <span style=\"color: #0000DF;\"><span style=\"font-weight:bold;\">[逢坂大河]</span></span>        [td]-[/td]        忍野忍<br>ARENA 05: <span style=\"color: #0000DF;\"><span style=\"font-weight:bold;\">[白石うらら]</span></span>        [td]-[/td]        宮水三葉<br>ARENA 06: <span style=\"color: #0000DF;\"><span style=\"font-weight:bold;\">[金色の闇]</span></span>        [td]-[/td]        ヘスティア<br>ARENA 07: 四糸乃        [td]-[/td]        <span style=\"color: #0000DF;\"><span style=\"font-weight:bold;\">[暁美ほむら]</span></span><br>ARENA 08: <span style=\"color: #0000DF;\"><span style=\"font-weight:bold;\">[宇佐美みずき]</span></span>        [td]-[/td]        小鳥遊六花<br>ARENA 09: 宮園かをり        [td]-[/td]        <span style=\"color: #0000DF;\"><span style=\"font-weight:bold;\">[羽川翼]</span></span><br>ARENA 10: <span style=\"color: #0000DF;\"><span style=\"font-weight:bold;\">[小野寺小咲]</span></span>        [td]-[/td]        C.C.<br>ARENA 11: <span style=\"color: #0000DF;\"><span style=\"font-weight:bold;\">[木之本桜]</span></span>        [td]-[/td]        ジブリール<br>ARENA 12: 古河渚        [td]-[/td]        <span style=\"color: #0000DF;\"><span style=\"font-weight:bold;\">[間桐桜]</span></span><br>ARENA 13: <span style=\"color: #0000DF;\"><span style=\"font-weight:bold;\">[我妻由乃]</span></span>        [td]-[/td]        食蜂操祈<br>ARENA 14: <span style=\"color: #0000DF;\"><span style=\"font-weight:bold;\">[椎名ましろ]</span></span>        [td]-[/td]        涼風青葉<br>ARENA 15: 滝本ひふみ        [td]-[/td]        <span style=\"color: #0000DF;\"><span style=\"font-weight:bold;\">[霞ヶ丘詩羽]</span></span><br>ARENA 16: 潮田渚        <span style=\"color: #FF0000;\"><span style=\"font-weight:bold;\">[棄権]</span></span>        平和島静雄<br>ARENA 17: <span style=\"color: #0000DF;\"><span style=\"font-weight:bold;\">[ハルヒロ]</span></span>        [td]-[/td]        菜月昴<br>ARENA 18: 綾崎ハヤテ        <span style=\"color: #FF0000;\"><span style=\"font-weight:bold;\">[棄権]</span></span>        太宰治<br>ARENA 19: <span style=\"color: #0000DF;\"><span style=\"font-weight:bold;\">[衛宮士郎]</span></span>        [td]-[/td]        ベル・クラネル<br>ARENA 20: 日向創        <span style=\"color: #FF0000;\"><span style=\"font-weight:bold;\">[棄権]</span></span>        坂本<br>ARENA 21: <span style=\"color: #0000DF;\"><span style=\"font-weight:bold;\">[折原臨也]</span></span>        [td]-[/td]        カミナ<br>ARENA 22: フェリックス・アーガイル        [td]-[/td]        <span style=\"color: #0000DF;\"><span style=\"font-weight:bold;\">[野崎梅太郎]</span></span><br>ARENA 23: 御狐神双熾        [td]-[/td]        <span style=\"color: #0000DF;\"><span style=\"font-weight:bold;\">[阿良々木暦]</span></span><br>ARENA 24: 有馬公生        <span style=\"color: #FF0000;\"><span style=\"font-weight:bold;\">[棄権]</span></span>        伊丹耀司<br>ARENA 25: 夜ト        <span style=\"color: #FF0000;\"><span style=\"font-weight:bold;\">[棄権]</span></span>        土間太平<br>ARENA 26: 天霧綾斗        [td]-[/td]        <span style=\"color: #0000DF;\"><span style=\"font-weight:bold;\">[高須竜児]</span></span><br>ARENA 27: エル・ローライト        <span style=\"color: #FF0000;\"><span style=\"font-weight:bold;\">[棄権]</span></span>        暁古城<br>ARENA 28: 影山飛雄        <span style=\"color: #FF0000;\"><span style=\"font-weight:bold;\">[棄権]</span></span>        アインズ・ウール・ゴウン<br>ARENA 29: <span style=\"color: #0000DF;\"><span style=\"font-weight:bold;\">[比企谷八幡]</span></span>        [td]-[/td]        真奥貞夫<br>ARENA 30: 内巻すばる        [td]-[/td]        <span style=\"color: #0000DF;\"><span style=\"font-weight:bold;\">[ランサー]</span></span><br>ARENA 31: クラウンピース        <span style=\"color: #FF0000;\"><span style=\"font-weight:bold;\">[棄権]</span></span>        水橋パルスィ<br>ARENA 32: <span style=\"color: #0000DF;\"><span style=\"font-weight:bold;\">[八雲藍]</span></span>        [td]-[/td]        洩矢諏訪子<br><br>感谢召唤。","sub":[]},{"avatar":"//lain.bgm.tv/pic/user/m/000/08/95/89561.jpg","floor":"#8","id":"1254400","time":"2017-6-24 08:17","userId":"upsuper","userName":"upsuper","userSign":"","message":"ARENA 01: <span style=\"color: #0000DF;\"><span style=\"font-weight:bold;\">[牧瀬紅莉栖]</span></span>        [td]-[/td]        平沢唯<br>ARENA 02: ロゥリィ・マーキュリー        [td]-[/td]        <span style=\"color: #0000DF;\"><span style=\"font-weight:bold;\">[アクア]</span></span><br>ARENA 03: <span style=\"color: #0000DF;\"><span style=\"font-weight:bold;\">[楪いのり]</span></span>        [td]-[/td]        アイちゃん<br>ARENA 04: 逢坂大河        [td]-[/td]        <span style=\"color: #0000DF;\"><span style=\"font-weight:bold;\">[忍野忍]</span></span><br>ARENA 05: 白石うらら        [td]-[/td]        <span style=\"color: #0000DF;\"><span style=\"font-weight:bold;\">[宮水三葉]</span></span><br>ARENA 06: <span style=\"color: #0000DF;\"><span style=\"font-weight:bold;\">[金色の闇]</span></span>        [td]-[/td]        ヘスティア<br>ARENA 07: 四糸乃        [td]-[/td]        <span style=\"color: #0000DF;\"><span style=\"font-weight:bold;\">[暁美ほむら]</span></span><br>ARENA 08: <span style=\"color: #0000DF;\"><span style=\"font-weight:bold;\">[宇佐美みずき]</span></span>        [td]-[/td]        小鳥遊六花<br>ARENA 09: <span style=\"color: #0000DF;\"><span style=\"font-weight:bold;\">[宮園かをり]</span></span>        [td]-[/td]        羽川翼<br>ARENA 10: <span style=\"color: #0000DF;\"><span style=\"font-weight:bold;\">[小野寺小咲]</span></span>        [td]-[/td]        C.C.<br>ARENA 11: 木之本桜        [td]-[/td]        <span style=\"color: #0000DF;\"><span style=\"font-weight:bold;\">[ジブリール]</span></span><br>ARENA 12: <span style=\"color: #0000DF;\"><span style=\"font-weight:bold;\">[古河渚]</span></span>        [td]-[/td]        間桐桜<br>ARENA 13: 我妻由乃        [td]-[/td]        <span style=\"color: #0000DF;\"><span style=\"font-weight:bold;\">[食蜂操祈]</span></span><br>ARENA 14: 椎名ましろ        [td]-[/td]        <span style=\"color: #0000DF;\"><span style=\"font-weight:bold;\">[涼風青葉]</span></span><br>ARENA 15: <span style=\"color: #0000DF;\"><span style=\"font-weight:bold;\">[滝本ひふみ]</span></span>        [td]-[/td]        霞ヶ丘詩羽<br>ARENA 16: 潮田渚        <span style=\"color: #FF0000;\"><span style=\"font-weight:bold;\">[棄権]</span></span>        平和島静雄<br>ARENA 17: ハルヒロ        [td]-[/td]        <span style=\"color: #0000DF;\"><span style=\"font-weight:bold;\">[菜月昴]</span></span><br>ARENA 18: 綾崎ハヤテ        [td]-[/td]        <span style=\"color: #0000DF;\"><span style=\"font-weight:bold;\">[太宰治]</span></span><br>ARENA 19: <span style=\"color: #0000DF;\"><span style=\"font-weight:bold;\">[衛宮士郎]</span></span>        [td]-[/td]        ベル・クラネル<br>ARENA 20: <span style=\"color: #0000DF;\"><span style=\"font-weight:bold;\">[日向創]</span></span>        [td]-[/td]        坂本<br>ARENA 21: 折原臨也        <span style=\"color: #FF0000;\"><span style=\"font-weight:bold;\">[棄権]</span></span>        カミナ<br>ARENA 22: <span style=\"color: #0000DF;\"><span style=\"font-weight:bold;\">[フェリックス・アーガイル]</span></span>        [td]-[/td]        野崎梅太郎<br>ARENA 23: 御狐神双熾        [td]-[/td]        <span style=\"color: #0000DF;\"><span style=\"font-weight:bold;\">[阿良々木暦]</span></span><br>ARENA 24: <span style=\"color: #0000DF;\"><span style=\"font-weight:bold;\">[有馬公生]</span></span>        [td]-[/td]        伊丹耀司<br>ARENA 25: <span style=\"color: #0000DF;\"><span style=\"font-weight:bold;\">[夜ト]</span></span>        [td]-[/td]        土間太平<br>ARENA 26: 天霧綾斗        [td]-[/td]        <span style=\"color: #0000DF;\"><span style=\"font-weight:bold;\">[高須竜児]</span></span><br>ARENA 27: エル・ローライト        [td]-[/td]        <span style=\"color: #0000DF;\"><span style=\"font-weight:bold;\">[暁古城]</span></span><br>ARENA 28: 影山飛雄        <span style=\"color: #FF0000;\"><span style=\"font-weight:bold;\">[棄権]</span></span>        アインズ・ウール・ゴウン<br>ARENA 29: <span style=\"color: #0000DF;\"><span style=\"font-weight:bold;\">[比企谷八幡]</span></span>        [td]-[/td]        真奥貞夫<br>ARENA 30: <span style=\"color: #0000DF;\"><span style=\"font-weight:bold;\">[内巻すばる]</span></span>        [td]-[/td]        ランサー<br>ARENA 31: クラウンピース        <span style=\"color: #FF0000;\"><span style=\"font-weight:bold;\">[棄権]</span></span>        水橋パルスィ<br>ARENA 32: 八雲藍        <span style=\"color: #FF0000;\"><span style=\"font-weight:bold;\">[棄権]</span></span>        洩矢諏訪子<br><br>又是东方（","sub":[]},{"avatar":"//lain.bgm.tv/pic/user/m/000/17/36/173624.jpg","floor":"#9","id":"1254533","time":"2017-6-24 14:56","userId":"detao0452","userName":"Detao","userSign":"(困…)","message":"ARENA 01: <span style=\"color: #0000DF;\"><span style=\"font-weight:bold;\">[牧瀬紅莉栖]</span></span>        [td]-[/td]        平沢唯<br>ARENA 02: ロゥリィ・マーキュリー        [td]-[/td]        <span style=\"color: #0000DF;\"><span style=\"font-weight:bold;\">[アクア]</span></span><br>ARENA 03: <span style=\"color: #0000DF;\"><span style=\"font-weight:bold;\">[楪いのり]</span></span>        [td]-[/td]        アイちゃん<br>ARENA 04: <span style=\"color: #0000DF;\"><span style=\"font-weight:bold;\">[逢坂大河]</span></span>        [td]-[/td]        忍野忍<br>ARENA 05: 白石うらら        [td]-[/td]        <span style=\"color: #0000DF;\"><span style=\"font-weight:bold;\">[宮水三葉]</span></span><br>ARENA 06: <span style=\"color: #0000DF;\"><span style=\"font-weight:bold;\">[金色の闇]</span></span>        [td]-[/td]        ヘスティア<br>ARENA 07: 四糸乃        [td]-[/td]        <span style=\"color: #0000DF;\"><span style=\"font-weight:bold;\">[暁美ほむら]</span></span><br>ARENA 08: 宇佐美みずき        [td]-[/td]        [coloar=#0000DF]<span style=\"font-weight:bold;\">[小鳥遊六花]</span><br>ARENA 09: <span style=\"color: #0000DF;\"><span style=\"font-weight:bold;\">[宮園かをり]</span></span>        [td]-[/td]        羽川翼<br>ARENA 10: <span style=\"color: #0000DF;\"><span style=\"font-weight:bold;\">[小野寺小咲]</span></span>        [td]-[/td]        C.C.<br>ARENA 11: <span style=\"color: #0000DF;\"><span style=\"font-weight:bold;\">[木之本桜]</span></span>        [td]-[/td]        ジブリール<br>ARENA 12: <span style=\"color: #0000DF;\"><span style=\"font-weight:bold;\">[古河渚]</span></span>        [td]-[/td]        間桐桜<br>ARENA 13: 我妻由乃        [td]-[/td]        <span style=\"color: #0000DF;\"><span style=\"font-weight:bold;\">[食蜂操祈]</span></span><br>ARENA 14: <span style=\"color: #0000DF;\"><span style=\"font-weight:bold;\">[椎名ましろ]</span></span>        [td]-[/td]        涼風青葉<br>ARENA 15: 滝本ひふみ        <span style=\"color: #FF0000;\"><span style=\"font-weight:bold;\">[棄権]</span></span>        霞ヶ丘詩羽<br>ARENA 16: 潮田渚        <span style=\"color: #FF0000;\"><span style=\"font-weight:bold;\">[棄権]</span></span>        平和島静雄<br>ARENA 17: ハルヒロ        <span style=\"color: #FF0000;\"><span style=\"font-weight:bold;\">[棄権]</span></span>        菜月昴<br>ARENA 18: 綾崎ハヤテ        <span style=\"color: #FF0000;\"><span style=\"font-weight:bold;\">[棄権]</span></span>        太宰治<br>ARENA 19: 衛宮士郎        <span style=\"color: #FF0000;\"><span style=\"font-weight:bold;\">[棄権]</span></span>        ベル・クラネル<br>ARENA 20: 日向創        <span style=\"color: #FF0000;\"><span style=\"font-weight:bold;\">[棄権]</span></span>        坂本<br>ARENA 21: 折原臨也        <span style=\"color: #FF0000;\"><span style=\"font-weight:bold;\">[棄権]</span></span>        カミナ<br>ARENA 22: フェリックス・アーガイル        [td]-[/td]        <span style=\"color: #0000DF;\"><span style=\"font-weight:bold;\">[野崎梅太郎]</span></span><br>ARENA 23: 御狐神双熾        [td]-[/td]        <span style=\"color: #0000DF;\"><span style=\"font-weight:bold;\">[阿良々木暦]</span></span><br>ARENA 24: <span style=\"color: #0000DF;\"><span style=\"font-weight:bold;\">[有馬公生]</span></span>        [td]-[/td]        伊丹耀司<br>ARENA 25: 夜ト        <span style=\"color: #FF0000;\"><span style=\"font-weight:bold;\">[棄権]</span></span>        土間太平<br>ARENA 26: 天霧綾斗        [td]-[/td]        <span style=\"color: #0000DF;\"><span style=\"font-weight:bold;\">[高須竜児]</span></span><br>ARENA 27: <span style=\"color: #0000DF;\"><span style=\"font-weight:bold;\">[エル・ローライト]</span></span>        [td]-[/td]        暁古城<br>ARENA 28: 影山飛雄        <span style=\"color: #FF0000;\"><span style=\"font-weight:bold;\">[棄権]</span></span>        アインズ・ウール・ゴウン<br>ARENA 29: <span style=\"color: #0000DF;\"><span style=\"font-weight:bold;\">[比企谷八幡]</span></span>        [td]-[/td]        真奥貞夫<br>ARENA 30: 内巻すばる        [td]-[/td]        <span style=\"color: #0000DF;\"><span style=\"font-weight:bold;\">[ランサー]</span></span><br>ARENA 31: クラウンピース        <span style=\"color: #FF0000;\"><span style=\"font-weight:bold;\">[棄権]</span></span>        水橋パルスィ<br>ARENA 32: 八雲藍        <span style=\"color: #FF0000;\"><span style=\"font-weight:bold;\">[棄権]</span></span>        洩矢諏訪子<br><br>谢谢","sub":[]},{"avatar":"//lain.bgm.tv/pic/user/m/000/00/49/4916.jpg","floor":"#10","id":"1254592","time":"2017-6-24 19:03","userId":"magicat","userName":"猫乃魔物","userSign":"(恶心死了)","message":"擂台 01: <span style=\"color: #0000DF;\"><span style=\"font-weight:bold;\">[牧濑红莉栖]</span></span>        [td]-[/td]        平泽唯<br>擂台 02: <span style=\"color: #0000DF;\"><span style=\"font-weight:bold;\">[萝莉·麦丘利]</span></span>        [td]-[/td]        阿库娅<br>擂台 03: <span style=\"color: #0000DF;\"><span style=\"font-weight:bold;\">[楪祈]</span></span>        [td]-[/td]        小爱<br>擂台 04: <span style=\"color: #0000DF;\"><span style=\"font-weight:bold;\">[逢坂大河]</span></span>        [td]-[/td]        忍野忍<br>擂台 05: <span style=\"color: #0000DF;\"><span style=\"font-weight:bold;\">[白石丽]</span></span>        [td]-[/td]        宫水三叶<br>擂台 06: <span style=\"color: #0000DF;\"><span style=\"font-weight:bold;\">[金色暗影]</span></span>        [td]-[/td]        赫斯缇雅<br>擂台 07: 四糸乃        [td]-[/td]        <span style=\"color: #0000DF;\"><span style=\"font-weight:bold;\">[晓美焰]</span></span><br>擂台 08: <span style=\"color: #0000DF;\"><span style=\"font-weight:bold;\">[宇佐美瑞希]</span></span>        [td]-[/td]        小鸟游六花<br>擂台 09: <span style=\"color: #0000DF;\"><span style=\"font-weight:bold;\">[宫园薰]</span></span>        [td]-[/td]        羽川翼<br>擂台 10: 小野寺小咲        [td]-[/td]        <span style=\"color: #0000DF;\"><span style=\"font-weight:bold;\">[C.C.]</span></span><br>擂台 11: <span style=\"color: #0000DF;\"><span style=\"font-weight:bold;\">[木之本樱]</span></span>        [td]-[/td]        吉普莉尔<br>擂台 12: <span style=\"color: #0000DF;\"><span style=\"font-weight:bold;\">[古河渚]</span></span>        [td]-[/td]        间桐樱<br>擂台 13: 我妻由乃        [td]-[/td]        <span style=\"color: #0000DF;\"><span style=\"font-weight:bold;\">[食蜂操祈]</span></span><br>擂台 14: 椎名真白        <span style=\"color: #FF0000;\"><span style=\"font-weight:bold;\">[弃权]</span></span>        凉风青叶<br>擂台 15: 泷本日富美        <span style=\"color: #FF0000;\"><span style=\"font-weight:bold;\">[弃权]</span></span>        霞之丘诗羽<br>擂台 16: 潮田渚        <span style=\"color: #FF0000;\"><span style=\"font-weight:bold;\">[弃权]</span></span>        平和岛静雄<br>擂台 17: 哈尔希洛        <span style=\"color: #FF0000;\"><span style=\"font-weight:bold;\">[弃权]</span></span>        菜月昴<br>擂台 18: 绫崎飒        <span style=\"color: #FF0000;\"><span style=\"font-weight:bold;\">[弃权]</span></span>        太宰治<br>擂台 19: 卫宫士郎        <span style=\"color: #FF0000;\"><span style=\"font-weight:bold;\">[弃权]</span></span>        贝尔·克朗尼<br>擂台 20: 日向创        <span style=\"color: #FF0000;\"><span style=\"font-weight:bold;\">[弃权]</span></span>        坂本<br>擂台 21: 折原临也        <span style=\"color: #FF0000;\"><span style=\"font-weight:bold;\">[弃权]</span></span>        卡米那<br>擂台 22: 菲利克斯·阿盖尔        <span style=\"color: #FF0000;\"><span style=\"font-weight:bold;\">[弃权]</span></span>        野崎梅太郎<br>擂台 23: 御狐神双炽        <span style=\"color: #FF0000;\"><span style=\"font-weight:bold;\">[弃权]</span></span>        阿良良木历<br>擂台 24: 有马公生        <span style=\"color: #FF0000;\"><span style=\"font-weight:bold;\">[弃权]</span></span>        伊丹耀司<br>擂台 25: 夜斗        <span style=\"color: #FF0000;\"><span style=\"font-weight:bold;\">[弃权]</span></span>        土间太平<br>擂台 26: 天雾绫斗        <span style=\"color: #FF0000;\"><span style=\"font-weight:bold;\">[弃权]</span></span>        高须龙儿<br>擂台 27: L Lawliet        <span style=\"color: #FF0000;\"><span style=\"font-weight:bold;\">[弃权]</span></span>        晓古城<br>擂台 28: 影山飞雄        <span style=\"color: #FF0000;\"><span style=\"font-weight:bold;\">[弃权]</span></span>        安兹·乌尔·恭<br>擂台 29: 比企谷八幡        <span style=\"color: #FF0000;\"><span style=\"font-weight:bold;\">[弃权]</span></span>        真奥贞夫<br>擂台 30: 內卷昴        <span style=\"color: #FF0000;\"><span style=\"font-weight:bold;\">[弃权]</span></span>        Lancer<br>擂台 31: 克劳恩皮丝        [td]-[/td]        <span style=\"color: #0000DF;\"><span style=\"font-weight:bold;\">[水桥帕露希]</span></span><br>擂台 32: <span style=\"color: #0000DF;\"><span style=\"font-weight:bold;\">[八云蓝]</span></span>        [td]-[/td]        洩矢諏访子<br><br>感谢召唤","sub":[]}]