{"id":341879,"avatar":"//lain.bgm.tv/pic/user/m/000/01/43/14382.jpg","floor":"#1","group":"靠谱人生茶话会","groupHref":"/group/boring","groupThumb":"//lain.bgm.tv/pic/icon/m/000/00/03/364.jpg","message":"<a href=\"http://bbs.saraba1st.com/2b/thread-1358894-1-1.html\" target=\"_blank\" rel=\"nofollow external noopener\" class=\"l\">我语文不好，到底有没有阀值这个说法</a> - S1<br><a href=\"https://www.zhihu.com/question/42234873\" target=\"_blank\" rel=\"nofollow external noopener\" class=\"l\">有多少人明显认识“荀彧”为什么还是要读成“苟或”？ - 知乎</a><br>担忧，万一错的使用者太多会不会像空穴来风那样变成对的呢。<br><a href=\"http://lain.bgm.tv/pic/crt/l/5b/55/22898_crt_4C9dr.jpg?r=1483502590\" target=\"_blank\" rel=\"nofollow external noopener\" class=\"l\"><img src=\"http://lain.bgm.tv/pic/crt/m/5b/55/22898_crt_4C9dr.jpg?r=1483502590\" class=\"code\" alt></a><a href=\"http://bgm.tv/character/22898\" target=\"_blank\" rel=\"nofollow external noopener\" class=\"l\">荀彧 |  恋姫†無双</a><br><br><a href=\"http://bbs.saraba1st.com/2b/thread-1346386-1-1.html\" target=\"_blank\" rel=\"nofollow external noopener\" class=\"l\">其实风应该发fong音吧</a> - S1<br><a href=\"https://www.zhihu.com/question/20493313\" target=\"_blank\" rel=\"nofollow external noopener\" class=\"l\">为什么很多人习惯把「风」读成「fong」而不是「feng」？ - 知乎</a><br>Typhoon. 好像也没问题。 ","time":"2017-1-1 18:40","title":"阀值，苟或，冲钱，高清重置，床第之间，风（fong）…","userId":"laoism","userName":"林卯","userSign":"(✨️VIP 8✨️)"}