{"id":6122,"avatar":"//lain.bgm.tv/pic/user/m/000/00/51/5191.jpg","floor":"#1","group":"靠谱人生茶话会","groupHref":"/group/boring","groupThumb":"//lain.bgm.tv/pic/icon/m/000/00/03/364.jpg","message":"想看一下有多少人放心用这东西来存自己命根，个人觉得，密码这东西保存在服务器上非常不靠谱，无论这东西加密有多么牛，还不是靠主密码来保护，钓个鱼什么的或许还能搞到你的主密码，既然密码通过加密保存在网上，那是不是说我有你的主密码你就没命了，这个叫xxx的人，由于密码全都交由LastPass来保存，那他完整的网络身份直接就可以被别人拿来用了，这相对于离线保存来说，至少少了服务器上的风险，你好歹也要先把PC给破了才能开始找密码，用离线加密你还要破解一轮。<br><br><span style=\"color: red;\">上面的话看不看也罢了，问两个问题</span><br>LastPass如果在没有网络的地方是不是连做xxx这个人都不行了，还是说密码文件是本地一份，服务器也同步一份呢<br>既然有使用LastPass那么密码都是通过机器来生成的吧，如果使用这种无序密码，那到别的地方你不就上不了了吗，谁会为了登陆看个帖在别人的电脑下个LastPass啊 ","time":"2011-6-10 11:37","title":"有多少人是用LastPass记密码的？","userId":"wwftherocksp","userName":"Tr.","userSign":""}