{"id":411734,"avatar":"//lain.bgm.tv/pic/user/m/000/67/19/671967.jpg","floor":"#1","group":"靠谱人生茶话会","groupHref":"/group/boring","groupThumb":"//lain.bgm.tv/pic/icon/m/000/00/03/364.jpg","message":"10.18，拿快递的时候把手机给摔了，是我第一台手机(20年7月买的一加8)，之前摔过很多次了，背板早碎了，但这次摔到正面了，虽然内屏没事但快半个屏幕因为碎玻璃的纹路看不清了，想了一下干脆换手机得了<br><br>当天晚上，原价下单iqqo z9t+，啥也不懂主要就是看电池挺大的，看到老伙计的“惨状”让我的情绪很复杂，总之买的时候很急，用了一段时候才开始后悔，很多方面，买贵了、续航没到预期、新出的真我neo7很吸引我<br><br>然后就去爱回收、闪小白看了下，差不多亏700，就挺恼火的，想问一下有啥推荐的平台/渠道么，能少亏点","time":"2024-12-12 03:50","title":"用了不到两个月的新手机想换了，什么渠道能亏损最小化","userId":"671967","userName":"ヨルシカ","userSign":""}