{"id":366840,"avatar":"//lain.bgm.tv/pic/user/m/000/46/23/462354.jpg","floor":"#1","group":"靠谱人生茶话会","groupHref":"/group/boring","groupThumb":"//lain.bgm.tv/pic/icon/m/000/00/03/364.jpg","message":"联动隔壁<a href=\"https://bangumi.tv/group/topic/366835\" target=\"_blank\" rel=\"nofollow external noopener noreferrer\" class=\"l\">年度听歌报告</a>帖子<br>网易云的听歌报告虽然做得很烂但是有个歌词关键词总结机制，基本上就是给歌词中反复出现的名词计数，结果发现大家的报告中出现的词语往往都很相似，而且同一个人不同年度的听歌报告（还似乎无关他是否总是倾向去听全新的曲子）中出现的关键词也往往是循环反复的，比如个人从使用这个数据总结功能开始，每年的关键词不是“未来”就是“世界”。<br>从创作角度来说，不同创作者在根据某一歌曲类型创作歌词时一定会有逻辑上的相同倾向，而这种倾向会导致某些单词反复出现。这种思路上的相似性能够比较明确地说明大家在使用歌曲作为表达方式时追求的共性，而讨论为何会出现这些相同的意向、这些意向又是否拥有共同的指向也一定是一件很有趣的事情。<br>你印象中最常见的歌曲意向是什么呢？你又是怎么看待这个意向会出现的缘由呢？ ","time":"2021-12-27 15:54","title":"歌词中最常见的意向是什么","userId":"462354","userName":"夷蹴而就","userSign":"(当你长大，会成为绝望者、失败者与被诅咒者的拯救者吗？ . ...)"}