{"id":393318,"avatar":"//lain.bgm.tv/pic/user/m/000/43/79/437960.jpg","floor":"#1","group":"～技术宅真可怕～","groupHref":"/group/a","groupThumb":"//lain.bgm.tv/pic/icon/m/000/00/00/11.jpg","message":"班固米条目下的用户生产内容是主站除开数据库功能之外最为宝库的部分。但长期以来，只支持时间顺序的吐槽、日志展示机制，使得高质量的漫评很快被淹没在其他芜杂的信息之中。<br><br>往前发布的基于众包的 <a href=\"https://bgm.tv/group/topic/384510\" target=\"_blank\" rel=\"nofollow external noopener noreferrer\" class=\"l\">吐槽贴贴统计+短评时间线</a> 并上 <a href=\"https://bgm.tv/group/topic/380919\" target=\"_blank\" rel=\"nofollow external noopener noreferrer\" class=\"l\">bgmFeelingLucky</a>，提供了在相对长的时间跨度上精选优秀短评的机制，而另一方面、优秀的长评依旧被时间冲刷走。<br><br>今天发布的功能 <span style=\"font-weight:bold;\">长评推荐与日志广场</span> 就致力于解决这一问题：将允许用户在日志页面内主动推荐优秀的长评日志，被推荐的日志也将会出现在首页时间线的日志广场上。<br><br>  <img src=\"//lain.bgm.tv/pic/photo/l/32/c1/437960_wWZJA.jpg\" class=\"code\" alt><br><br>为了方便归档和后来用户的检索、鼓励创作高质量长评，我们企划并设计了 <span style=\"font-weight:bold;\">半月刊以及徽章系统</span>：一段时间内经过筛选的优秀长评将被收纳进 <span style=\"font-weight:bold;\">bangumi半月刊</span>，并且装饰以 <span style=\"font-weight:bold;\">徽章</span> 在日志页面。<br><br>  <img src=\"//lain.bgm.tv/pic/photo/l/32/c1/437960_mjyJ2.jpg\" class=\"code\" alt><br><br>具体实践上、每期半月刊收纳的长评日志将以链接合集的形式发布在 <a href=\"https://bgm.tv/group/biweekly\" target=\"_blank\" rel=\"nofollow external noopener noreferrer\" class=\"l\">半月刊小组</a> 中。<a href=\"https://bgm.tv/group/topic/393210\" target=\"_blank\" rel=\"nofollow external noopener noreferrer\" class=\"l\">首期半月刊</a> 已经发布、欢迎前往阅览。<br><br>如果你也喜欢阅读优秀的短评与长篇漫评、欢迎启用小组件 <a href=\"https://bgm.tv/dev/app/2720\" target=\"_blank\" rel=\"nofollow external noopener noreferrer\" class=\"l\">短评贴贴enhance | 半月刊</a> 体验相关功能。欢迎提出建议与bug反馈。<br><br><span style=\"text-decoration: line-through;\">后排提问，怎么才能在不需要加好友的情况下成功@</span>","time":"2024-2-5 02:47","title":"【New Feature】长评推荐与日志广场、半月刊以及徽章系统","userId":"neutrinoliu","userName":"徒手开根号二","userSign":"(nobody cares.)"}