{"id":5385,"avatar":"//lain.bgm.tv/pic/user/m/000/00/93/9302.jpg","floor":"#1","group":"番組WIKI計画","groupHref":"/group/wiki","groupThumb":"//lain.bgm.tv/pic/icon/m/000/00/01/128.jpg","message":"启动“编辑”模式：<br>比如从Amazon抓取条目后，每个页面打开时是直接进入编辑页面，而不是显示页面。<br>又比如，在选择条目里的“信息”时，也是直接进入编辑，而不是先到信息显示页，再点击编辑。<br>还有就是编辑时默认是wiki模式，不是入门模式<br><br><br>另，关于系列书籍漫画，能不能设定一个小的继承关系，设定关联后，可以自动把作者，原作，出版社添加到单行本里，如果有不同的可以在单行本里更改。 ","time":"2011-4-26 13:41","title":"小建议：给用户设置“编辑”模式，进入模式后所有页面都默认是进入编辑","userId":"youyue","userName":"utt","userSign":""}