[{"avatar":"//lain.bgm.tv/pic/user/m/000/14/27/142735.jpg","floor":"#2","id":"1550091","time":"2020-1-18 10:46","userId":"z55456489","userName":"ofo","userSign":"(ofo)","message":"30年","sub":[]},{"avatar":"//lain.bgm.tv/pic/user/m/000/04/97/49777.jpg","floor":"#3","id":"1550092","time":"2020-1-18 10:58","userId":"bgmouse","userName":"MousHu","userSign":"(miaow~~~)","message":"这逗号前后的反差感 感觉让这问题多了些风味 hhh","sub":[]},{"avatar":"//lain.bgm.tv/pic/user/m/000/31/07/310722.jpg","floor":"#4","id":"1550093","time":"2020-1-18 11:00","userId":"maple_5233","userName":"桜小路ルナ","userSign":"(大変に気分がいい)","message":"2020-1990=30","sub":[]}]