{"id":365627,"avatar":"//lain.bgm.tv/pic/user/m/000/46/23/462354.jpg","floor":"#1","group":"番组开发","groupHref":"/group/dev","groupThumb":"//lain.bgm.tv/pic/icon/m/000/00/41/4180.jpg?r=1519373244","message":"简单来说就是不喜欢某部作品，就把那部作品和提及该作品的所有话题全部屏蔽的插件？<br>打个比方：我不喜欢并抵制随地吐痰的人，也不愿看到有同类人讨论“随地吐痰的人有多么帅气”“不喜欢随地吐痰的人都是脑子有病伪作清高”之类，简单来说就是主动保持距离，眼不见为净，不给自己找罪受。<br><br>*当然如果有更强的进化版本例如“将为xx条目评分x分以上的所有用户全部屏蔽”之类的插件也请务必给予指路，虽然我知道自己应该是在做梦 ","time":"2021-10-18 21:21","title":"有没有屏蔽某个收录条目的插件","userId":"462354","userName":"夷蹴而就","userSign":"(当你长大，会成为绝望者、失败者与被诅咒者的拯救者吗？ ...)"}